{
  "data": [
    {
      "word": "alic",
      "count": 4
    },
    {
      "word": "rabbit",
      "count": 4
    },
    {
      "word": "get",
      "count": 2
    },
    {
      "word": "sister",
      "count": 2
    },
    {
      "word": "noth",
      "count": 2
    },
    {
      "word": "book",
      "count": 2
    },
    {
      "word": "pictur",
      "count": 2
    },
    {
      "word": "convers",
      "count": 2
    },
    {
      "word": "thought",
      "count": 2
    },
    {
      "word": "mind",
      "count": 2
    },
    {
      "word": "ran",
      "count": 2
    },
    {
      "word": "oh",
      "count": 2
    },
    {
      "word": "dear",
      "count": 2
    },
    {
      "word": "time",
      "count": 2
    },
    {
      "word": "watch",
      "count": 2
    },
    {
      "word": "across",
      "count": 2
    },
    {
      "word": "begin",
      "count": 1
    },
    {
      "word": "tire",
      "count": 1
    },
    {
      "word": "sit",
      "count": 1
    },
    {
      "word": "bank",
      "count": 1
    },
    {
      "word": "twice",
      "count": 1
    },
    {
      "word": "peep",
      "count": 1
    },
    {
      "word": "read",
      "count": 1
    },
    {
      "word": "use",
      "count": 1
    },
    {
      "word": "without",
      "count": 1
    },
    {
      "word": "consid",
      "count": 1
    },
    {
      "word": "well",
      "count": 1
    },
    {
      "word": "could",
      "count": 1
    },
    {
      "word": "hot",
      "count": 1
    },
    {
      "word": "day",
      "count": 1
    },
    {
      "word": "made",
      "count": 1
    },
    {
      "word": "feel",
      "count": 1
    },
    {
      "word": "sleepi",
      "count": 1
    },
    {
      "word": "stupid",
      "count": 1
    },
    {
      "word": "whether",
      "count": 1
    },
    {
      "word": "pleasur",
      "count": 1
    },
    {
      "word": "make",
      "count": 1
    },
    {
      "word": "daisychain",
      "count": 1
    },
    {
      "word": "would",
      "count": 1
    },
    {
      "word": "worth",
      "count": 1
    },
    {
      "word": "troubl",
      "count": 1
    },
    {
      "word": "pick",
      "count": 1
    },
    {
      "word": "daisi",
      "count": 1
    },
    {
      "word": "suddenli",
      "count": 1
    },
    {
      "word": "white",
      "count": 1
    },
    {
      "word": "pink",
      "count": 1
    },
    {
      "word": "eye",
      "count": 1
    },
    {
      "word": "close",
      "count": 1
    },
    {
      "word": "remark",
      "count": 1
    },
    {
      "word": "think",
      "count": 1
    },
    {
      "word": "much",
      "count": 1
    },
    {
      "word": "way",
      "count": 1
    },
    {
      "word": "hear",
      "count": 1
    },
    {
      "word": "say",
      "count": 1
    },
    {
      "word": "shall",
      "count": 1
    },
    {
      "word": "late",
      "count": 1
    },
    {
      "word": "afterward",
      "count": 1
    },
    {
      "word": "occur",
      "count": 1
    },
    {
      "word": "ought",
      "count": 1
    },
    {
      "word": "wonder",
      "count": 1
    },
    {
      "word": "seem",
      "count": 1
    },
    {
      "word": "quit",
      "count": 1
    },
    {
      "word": "natur",
      "count": 1
    },
    {
      "word": "actual",
      "count": 1
    },
    {
      "word": "took",
      "count": 1
    },
    {
      "word": "waistcoat",
      "count": 1
    },
    {
      "word": "pocket",
      "count": 1
    },
    {
      "word": "look",
      "count": 1
    },
    {
      "word": "hurri",
      "count": 1
    },
    {
      "word": "start",
      "count": 1
    },
    {
      "word": "feet",
      "count": 1
    },
    {
      "word": "flash",
      "count": 1
    },
    {
      "word": "never",
      "count": 1
    },
    {
      "word": "seen",
      "count": 1
    },
    {
      "word": "either",
      "count": 1
    },
    {
      "word": "waistcoatpocket",
      "count": 1
    },
    {
      "word": "take",
      "count": 1
    },
    {
      "word": "burn",
      "count": 1
    },
    {
      "word": "curios",
      "count": 1
    },
    {
      "word": "field",
      "count": 1
    },
    {
      "word": "fortun",
      "count": 1
    },
    {
      "word": "see",
      "count": 1
    },
    {
      "word": "pop",
      "count": 1
    },
    {
      "word": "larg",
      "count": 1
    },
    {
      "word": "rabbithol",
      "count": 1
    },
    {
      "word": "hedg",
      "count": 1
    }
  ]
}